pgmate/__init__.py
pgmate/core.py
pgmate-0.1.0.dist-info/licenses/LICENSE
pgmate-0.1.0.dist-info/METADATA
pgmate-0.1.0.dist-info/WHEEL
pgmate-0.1.0.dist-info/top_level.txt
pgmate-0.1.0.dist-info/RECORD
