Metadata-Version: 2.4
Name: pgmate
Version: 0.1.0
Summary: PostgreSQL All-in-One Toolkit (Queue + Cron + KV Store + PubSub)
Author-email: PgMate Authors <author@example.com>
License: MIT
Project-URL: Homepage, https://github.com/zhenchuan/PgKit
Project-URL: Bug Tracker, https://github.com/zhenchuan/PgKit/issues
Classifier: Programming Language :: Python :: 3
Classifier: License :: OSI Approved :: MIT License
Classifier: Operating System :: OS Independent
Classifier: Topic :: Database
Classifier: Topic :: Software Development :: Libraries :: Python Modules
Requires-Python: >=3.8
License-File: LICENSE
Requires-Dist: psycopg2-binary>=2.9.0
Dynamic: license-file
